virtualtryon_api_common/__init__.py
virtualtryon_api_common/fastapi_helper.py
virtualtryon_api_common/jwt_helper.py
virtualtryon_api_common/supabase_helper.py
virtualtryon_api_common-0.1.8.dist-info/METADATA
virtualtryon_api_common-0.1.8.dist-info/WHEEL
virtualtryon_api_common-0.1.8.dist-info/RECORD
