Metadata-Version: 2.1
Name: virtualtryon_api_common
Version: 0.1.8
Summary: Common functionality across micro APIs
Author: sinapy
Author-email: sinasarsharpour@cmail.carleton.ca
Requires-Python: >=3.10,<4.0
Classifier: Programming Language :: Python :: 3
Classifier: Programming Language :: Python :: 3.10
Classifier: Programming Language :: Python :: 3.11
Classifier: Programming Language :: Python :: 3.12
Requires-Dist: auth (>=0.5.3,<0.6.0)
Requires-Dist: fastapi[standard] (>=0.113.0,<0.114.0)
Requires-Dist: pyjwt (>=2.10.1,<3.0.0)
Requires-Dist: supabase (>=2.10.0,<3.0.0)
